model_rotator/__init__.py
model_rotator/rotator.py
model_rotator-0.1.3.dist-info/LICENSE
model_rotator-0.1.3.dist-info/METADATA
model_rotator-0.1.3.dist-info/WHEEL
model_rotator-0.1.3.dist-info/RECORD
