Metadata-Version: 2.1
Name: model-rotator
Version: 0.1.3
Summary: rotates models to avoid hitting rate limit
Author: tikendraw
Author-email: tikendraksahu1029@gmail.com
Requires-Python: >=3.12,<4.0
Classifier: Programming Language :: Python :: 3
Classifier: Programming Language :: Python :: 3.12
Project-URL: homepage, https://github.com/tikendraw/model-rotator
Project-URL: repository, https://github.com/tikendraw/model-rotator
